{
  "type": "unknown",
  "name": "JvmWildcard",
  "signature": "@Target([AnnotationTarget.TYPE]) annotation class JvmWildcard",
  "items": [
    {
      "text": "<init>()",
      "desc": "Instructs compiler to generate wildcard for annotated type arguments corresponding to parameters with declaration-site variance."
    },
    {
      "text": "val <T : Annotation> T.annotationClass: KClass<out T>",
      "desc": "Returns a KClass instance corresponding to the annotation type of this annotation."
    }
  ]
}